cron_mon/__init__.py
cron_mon/exceptions.py
cron_mon/monitor.py
cron_mon/py.typed
cron_mon_py-0.2.1.dist-info/METADATA
cron_mon_py-0.2.1.dist-info/WHEEL
cron_mon_py-0.2.1.dist-info/RECORD
