Metadata-Version: 2.3
Name: cron-mon-py
Version: 0.2.1
Summary: A simple integration for CronMon
Project-URL: Homepage, https://github.com/cron-mon-io/cron-mon-py
Project-URL: Documentation, https://cron-mon-py.readthedocs.io
Requires-Python: >=3.9
Requires-Dist: requests>=2.30
Requires-Dist: types-requests>=2.32.0.20240914
